phase_extender/__init__.py
phase_extender/__main__.py
phase_extender/arg_builders.py
phase_extender/compute_score.py
phase_extender/hapstats.py
phase_extender/phase_extender.py
phase_extender/phaser.py
phase_extender/utils.py
phase_extender/val_extractor.py
phase_extender-0.1.8.dist-info/METADATA
phase_extender-0.1.8.dist-info/WHEEL
phase_extender-0.1.8.dist-info/entry_points.txt
phase_extender-0.1.8.dist-info/top_level.txt
phase_extender-0.1.8.dist-info/RECORD
