Metadata-Version: 2.1
Name: phase-extender
Version: 0.1.8
Summary: A python program that uses ReadBack phased haplotypes in population of samples and returns extended haplotype blocks.
Home-page: https://github.com/everestial/phase-Extender
Author: Bishwa K. Giri
Author-email: kirannbishwa01@gmail.com
License: UNKNOWN
Project-URL: Bug Tracker, https://github.com/everestial/phase-Extender
Platform: UNKNOWN
Classifier: Programming Language :: Python :: 3
Classifier: License :: OSI Approved :: MIT License
Classifier: Operating System :: OS Independent
Requires-Python: >=3.7
Requires-Dist: numpy (>=1.22)
Requires-Dist: matplotlib (>=3)
Requires-Dist: pandas (>=1)
Requires-Dist: seaborn
